{"id":"place.429025461","type":"Feature","place_type":["place"],"relevance":1.0,"properties":{"accuracy":"","mapbox_id":"dXJuOm1ieHBsYzpHWkpvdFE","wikidata":"Q270","category":"","address":"","foursquare":"","maki":""},"text_en":"Warsaw","place_name_en":"Warsaw, Masovian Voivodeship, Poland","text":"Warsaw","place_name":"Warsaw, Masovian Voivodeship, Poland","matching_place_name":"","center":[21.006725,52.231958],"geometry":{"type":"Point","coordinates":[21.006725,52.231958]},"address":"","context":[{"id":"region.58549","mapbox_id":"dXJuOm1ieHBsYzo1TFU","text_en":"Masovian Voivodeship","text":"Masovian Voivodeship","wikidata":"Q54169","language_en":"en","language":"en","short_code":"PL-14"},{"id":"country.8885","mapbox_id":"dXJuOm1ieHBsYzpJclU","text_en":"Poland","text":"Poland","wikidata":"Q36","language_en":"en","language":"en","short_code":"pl"}],"language_en":"en","language":"en","matching_text":""}