{
  "landusages" : [ {
    "type" : "residential",
    "area" : 0.20733231
  }, {
    "type" : "grass",
    "area" : 0.12157753
  }, {
    "type" : "water_geometry",
    "area" : 0.11369116
  }, {
    "type" : "wood",
    "area" : 0.09458112
  }, {
    "type" : "parking",
    "area" : 0.049496774
  }, {
    "type" : "railway",
    "area" : 0.03525458
  }, {
    "type" : "park",
    "area" : 0.03293248
  }, {
    "type" : "commercial",
    "area" : 0.032381132
  }, {
    "type" : "construction",
    "area" : 0.019474795
  }, {
    "type" : "yes",
    "area" : 0.018078277
  }, {
    "type" : "retail",
    "area" : 0.016910678
  }, {
    "type" : "forest",
    "area" : 0.015392309
  }, {
    "type" : "wetland",
    "area" : 0.01508459
  }, {
    "type" : "grassland",
    "area" : 0.014408997
  }, {
    "type" : "industrial",
    "area" : 0.010807898
  } ],
  "amenities" : [ {
    "type" : "road",
    "count" : 1850
  }, {
    "type" : "apartments",
    "count" : 264
  }, {
    "type" : "vending_machine",
    "count" : 109
  }, {
    "type" : "bench",
    "count" : 102
  }, {
    "type" : "outbuilding",
    "count" : 97
  }, {
    "type" : "retail",
    "count" : 67
  }, {
    "type" : "waste_basket",
    "count" : 65
  }, {
    "type" : "office",
    "count" : 47
  }, {
    "type" : "bicycle_parking",
    "count" : 40
  }, {
    "type" : "roof",
    "count" : 34
  }, {
    "type" : "fast_food",
    "count" : 26
  }, {
    "type" : "service",
    "count" : 24
  }, {
    "type" : "restaurant",
    "count" : 24
  }, {
    "type" : "school",
    "count" : 19
  }, {
    "type" : "bank",
    "count" : 16
  }, {
    "type" : "atm",
    "count" : 14
  }, {
    "type" : "commercial",
    "count" : 14
  }, {
    "type" : "garage",
    "count" : 13
  }, {
    "type" : "hospital",
    "count" : 12
  }, {
    "type" : "bicycle_rental",
    "count" : 10
  }, {
    "type" : "cafe",
    "count" : 9
  }, {
    "type" : "pharmacy",
    "count" : 9
  }, {
    "type" : "industrial",
    "count" : 8
  }, {
    "type" : "pub",
    "count" : 8
  }, {
    "type" : "parking_entrance",
    "count" : 8
  }, {
    "type" : "residential",
    "count" : 8
  }, {
    "type" : "elevator_housing",
    "count" : 8
  }, {
    "type" : "shed",
    "count" : 7
  }, {
    "type" : "doctors",
    "count" : 7
  }, {
    "type" : "grit_bin",
    "count" : 6
  }, {
    "type" : "post_box",
    "count" : 6
  }, {
    "type" : "dentist",
    "count" : 6
  }, {
    "type" : "construction",
    "count" : 5
  }, {
    "type" : "government",
    "count" : 5
  }, {
    "type" : "kindergarten",
    "count" : 5
  }, {
    "type" : "bar",
    "count" : 5
  }, {
    "type" : "toilets",
    "count" : 4
  }, {
    "type" : "public",
    "count" : 4
  }, {
    "type" : "fire_station",
    "count" : 4
  }, {
    "type" : "hotel",
    "count" : 4
  }, {
    "type" : "library",
    "count" : 3
  }, {
    "type" : "church",
    "count" : 3
  }, {
    "type" : "elvator_housing",
    "count" : 3
  }, {
    "type" : "kiosk",
    "count" : 3
  }, {
    "type" : "boathouse",
    "count" : 3
  }, {
    "type" : "presbytery",
    "count" : 3
  }, {
    "type" : "college",
    "count" : 3
  }, {
    "type" : "parcel_locker",
    "count" : 3
  }, {
    "type" : "monastery",
    "count" : 3
  }, {
    "type" : "chapel",
    "count" : 2
  }, {
    "type" : "museum",
    "count" : 2
  }, {
    "type" : "house",
    "count" : 2
  }, {
    "type" : "warehouse",
    "count" : 2
  }, {
    "type" : "charging_station",
    "count" : 2
  }, {
    "type" : "bicycle_repair_station",
    "count" : 2
  }, {
    "type" : "train_station",
    "count" : 2
  }, {
    "type" : "garages",
    "count" : 2
  }, {
    "type" : "recycling",
    "count" : 2
  }, {
    "type" : "theatre",
    "count" : 2
  }, {
    "type" : "post_office",
    "count" : 2
  }, {
    "type" : "taxi",
    "count" : 1
  }, {
    "type" : "lawyer",
    "count" : 1
  }, {
    "type" : "childcare",
    "count" : 1
  }, {
    "type" : "waste_disposal",
    "count" : 1
  }, {
    "type" : "internet_cafe",
    "count" : 1
  }, {
    "type" : "fuel",
    "count" : 1
  }, {
    "type" : "fountain",
    "count" : 1
  }, {
    "type" : "sports_centre",
    "count" : 1
  }, {
    "type" : "religious",
    "count" : 1
  }, {
    "type" : "no",
    "count" : 1
  }, {
    "type" : "public_building",
    "count" : 1
  }, {
    "type" : "locker",
    "count" : 1
  }, {
    "type" : "boat",
    "count" : 1
  }, {
    "type" : "ice_cream",
    "count" : 1
  }, {
    "type" : "police",
    "count" : 1
  }, {
    "type" : "townhall",
    "count" : 1
  }, {
    "type" : "training",
    "count" : 1
  }, {
    "type" : "parking",
    "count" : 1
  }, {
    "type" : "cosmetic_surgeon",
    "count" : 1
  }, {
    "type" : "place_of_worship",
    "count" : 1
  }, {
    "type" : "bureau_de_change",
    "count" : 1
  }, {
    "type" : "cathedral",
    "count" : 1
  }, {
    "type" : "static_caravan",
    "count" : 1
  } ],
  "places" : [ {
    "name" : "Osiedle Kijowska",
    "type" : "neighbourhood",
    "zOrder" : 5,
    "population" : 0,
    "tags" : {
      "name" : "Osiedle Kijowska",
      "place" : "neighbourhood"
    }
  }, {
    "name" : "Port Praski",
    "type" : "neighbourhood",
    "zOrder" : 5,
    "population" : 0,
    "tags" : {
      "name" : "Port Praski",
      "place" : "neighbourhood",
      "wikipedia" : "pl:Port Praski"
    }
  }, {
    "name" : "Stara Praga",
    "type" : "quarter",
    "zOrder" : 4,
    "population" : 0,
    "tags" : {
      "name:de" : "Alt-Praga",
      "name:uk" : "Стара Прага",
      "name" : "Stara Praga",
      "name:pl" : "Stara Praga",
      "place" : "quarter"
    }
  } ],
  "buildings" : {
    "totalArea" : 357545,
    "totalVolume" : 6339382,
    "count" : 805,
    "maxHeight" : 76.0
  },
  "roads" : [ {
    "type" : "cycleway",
    "count" : 56
  }, {
    "type" : "tertiary",
    "count" : 102
  }, {
    "type" : "tertiary_link",
    "count" : 2
  }, {
    "type" : "residential",
    "count" : 58
  }, {
    "type" : "service",
    "count" : 360
  }, {
    "type" : "path",
    "count" : 54
  }, {
    "type" : "pedestrian",
    "count" : 4
  }, {
    "type" : "primary",
    "count" : 2
  }, {
    "type" : "track",
    "count" : 14
  }, {
    "type" : "subway",
    "count" : 14
  }, {
    "type" : "living_street",
    "count" : 19
  }, {
    "type" : "secondary",
    "count" : 79
  }, {
    "type" : "secondary_link",
    "count" : 4
  }, {
    "type" : "steps",
    "count" : 117
  }, {
    "type" : "tram",
    "count" : 41
  }, {
    "type" : "rail",
    "count" : 57
  }, {
    "type" : "footway",
    "count" : 867
  } ],
  "connections" : 0,
  "status" : "OK",
  "version" : "1",
  "elevation" : {
    "min" : 76,
    "max" : 98,
    "diff50m" : 10
  }
}